slowlane/__init__.py
slowlane/asc/__init__.py
slowlane/asc/client.py
slowlane/auth/__init__.py
slowlane/auth/jwt_auth.py
slowlane/auth/playwright_login.py
slowlane/auth/session_auth.py
slowlane/cli/__init__.py
slowlane/cli/asc.py
slowlane/cli/env.py
slowlane/cli/main.py
slowlane/cli/signing.py
slowlane/cli/spaceauth.py
slowlane/cli/upload.py
slowlane/core/__init__.py
slowlane/core/config.py
slowlane/core/errors.py
slowlane/core/http.py
slowlane/core/secrets.py
slowlane/devportal/__init__.py
slowlane/devportal/client.py
slowlane/transporter/__init__.py
slowlane/transporter/wrapper.py
slowlane-0.1.0.dist-info/LICENSE
slowlane-0.1.0.dist-info/METADATA
slowlane-0.1.0.dist-info/WHEEL
slowlane-0.1.0.dist-info/entry_points.txt
slowlane-0.1.0.dist-info/RECORD
