Metadata-Version: 2.1
Name: slowlane
Version: 0.1.0
Summary: Python CLI tool for Apple service automation - fastlane-compatible authentication and App Store Connect/Developer Portal operations
License: MIT
Author: Slowlane Contributors
Requires-Python: >=3.11,<4.0
Classifier: License :: OSI Approved :: MIT License
Classifier: Programming Language :: Python :: 3
Classifier: Programming Language :: Python :: 3.11
Classifier: Programming Language :: Python :: 3.12
Classifier: Programming Language :: Python :: 3.13
Requires-Dist: click (>=8.3.1,<9.0.0)
Requires-Dist: cryptography (>=46.0.4,<47.0.0)
Requires-Dist: httpx (>=0.28.1,<0.29.0)
Requires-Dist: keyring (>=25.7.0,<26.0.0)
Requires-Dist: playwright (>=1.58.0,<2.0.0)
Requires-Dist: pyjwt (>=2.11.0,<3.0.0)
Requires-Dist: rich (>=14.3.1,<15.0.0)
Requires-Dist: tomli (>=2.4.0,<3.0.0)
Requires-Dist: tomli-w (>=1.2.0,<2.0.0)
Requires-Dist: typer (>=0.21.1,<0.22.0)
